anus/__init__.py
anus/shit/__init__.py
anus/shit/average_shit.py
anus/shit/base.py
anus/shit/big_shit.py
anus/shit/small_shit.py
anus-1.0.3.dist-info/LICENSE.md
anus-1.0.3.dist-info/METADATA
anus-1.0.3.dist-info/WHEEL
anus-1.0.3.dist-info/top_level.txt
anus-1.0.3.dist-info/RECORD
