Metadata-Version: 2.1
Name: anus
Version: 1.0.3
Summary: Just anus. That's it
Home-page: https://github.com/VoIlAlex/russian
Author: Ilya Vouk
Author-email: ilya.vouk@gmail.com
License: MIT
Platform: UNKNOWN
Classifier: Development Status :: 1 - Planning
Classifier: Programming Language :: Python :: 3.5
Classifier: Programming Language :: Python :: 3.6
Classifier: Programming Language :: Python :: 3.7
Classifier: Programming Language :: Python :: 3.8
License-File: LICENSE.md
